dearprudence/__init__.py
dearprudence/_version.py
dearprudence/core.py
dearprudence/errors.py
dearprudence/io.py
dearprudence/utils.py
dearprudence-1.1.0.dist-info/METADATA
dearprudence-1.1.0.dist-info/WHEEL
dearprudence-1.1.0.dist-info/licenses/LICENSE
dearprudence-1.1.0.dist-info/RECORD
