Metadata-Version: 2.1
Name: dearprudence
Version: 1.1.0
Summary: Internal Python library filled with sugar for swallowing downscalingCMIP6 parameter files
Project-URL: Homepage, https://github.com/brews/dearprudence
Project-URL: Bug Tracker, https://github.com/brews/dearprudence/issues
Author-email: Brewster Malevich <bmalevich@rhg.com>
License-File: LICENSE
Classifier: Intended Audience :: Developers
Classifier: Intended Audience :: Science/Research
Classifier: License :: OSI Approved :: Apache Software License
Classifier: Natural Language :: English
Classifier: Operating System :: OS Independent
Classifier: Programming Language :: Python :: 3
Classifier: Topic :: Scientific/Engineering
Requires-Python: >=3.9
Provides-Extra: catalog
Requires-Dist: intake-esm; extra == 'catalog'
Provides-Extra: test
Requires-Dist: black; extra == 'test'
Requires-Dist: mypy; extra == 'test'
Requires-Dist: pytest; extra == 'test'
Requires-Dist: pytest-cov; extra == 'test'
Requires-Dist: ruff; extra == 'test'
